CHANGELOG.rst
LICENSE.txt
MANIFEST.in
README.rst
VERSION.txt
setup.cfg
setup.py
pyramid_methodrewrite/__init__.py
pyramid_methodrewrite/test.py
pyramid_methodrewrite.egg-info/PKG-INFO
pyramid_methodrewrite.egg-info/SOURCES.txt
pyramid_methodrewrite.egg-info/dependency_links.txt
pyramid_methodrewrite.egg-info/requires.txt
pyramid_methodrewrite.egg-info/top_level.txt
pyramid_methodrewrite.egg-info/zip-safe