Metadata-Version: 1.1
Name: pyramid-methodrewrite
Version: 0.2.2
Summary: A pyramid plugin that rewrites the HTTP method based on a query-string parameter.
Home-page: http://github.com/cadithealth/pyramid_methodrewrite
Author: Philip J Grabner, Cadit Health Inc
Author-email: oss@cadit.com
License: MIT (http://opensource.org/licenses/MIT)
Keywords: web wsgi pyramid http method rewrite proxy work-around
Platform: UNKNOWN
Classifier: Intended Audience :: Developers
Classifier: Programming Language :: Python
Classifier: Framework :: Pyramid
Classifier: Environment :: Console
Classifier: Environment :: Web Environment
Classifier: Operating System :: OS Independent
Classifier: Topic :: Internet
Classifier: Topic :: Software Development
Classifier: Topic :: Internet :: WWW/HTTP
Classifier: Topic :: Internet :: WWW/HTTP :: WSGI
Classifier: Topic :: Software Development :: Libraries :: Application Frameworks
Classifier: Natural Language :: English
Classifier: License :: OSI Approved :: MIT License
Classifier: License :: Public Domain
